get_args_to_launch_editor.py
get_args_to_launch_editor-0.1.0a0.dist-info/licenses/LICENSE
get_args_to_launch_editor-0.1.0a0.dist-info/METADATA
get_args_to_launch_editor-0.1.0a0.dist-info/WHEEL
get_args_to_launch_editor-0.1.0a0.dist-info/top_level.txt
get_args_to_launch_editor-0.1.0a0.dist-info/RECORD
