Metadata-Version: 2.4
Name: get-args-to-launch-editor
Version: 0.1.0a0
Summary: A cross-platform Python utility to determine how to launch the user's preferred text editor, using user input, environment variables, and platform-specific fallbacks.
Author-email: Jifeng Wu <jifengwu2k@gmail.com>
License-Expression: MIT
Project-URL: Homepage, https://github.com/jifengwu2k/get-args-to-launch-editor
Project-URL: Bug Tracker, https://github.com/jifengwu2k/get-args-to-launch-editor/issues
Classifier: Programming Language :: Python :: 2
Classifier: Programming Language :: Python :: 3
Classifier: Operating System :: OS Independent
Requires-Python: >=2
License-File: LICENSE
Requires-Dist: find-executable
Requires-Dist: posix-or-nt
Requires-Dist: split-command-line
Dynamic: license-file
